{"ProjectWatches":"{\"Value\":[{\"Id\":\"ec5c07d3-00d5-47e9-b4df-f94a0ad51196\",\"Expression\":\"strFAName\"},{\"Id\":\"771589b2-08ce-4cd2-9987-d400158409b3\",\"Expression\":\"strLastInitial\"},{\"Id\":\"f24ca0fd-8fce-45a9-bf72-c51a5290f8b3\",\"Expression\":\"strFirstName\"}]}","LibraryProjectSettings":"{\"IncludeSourcesByDefault\":true,\"UseCompilerV2\":false,\"CompileExpressions\":true,\"DefaultActivitiesRootCategories\":[null]}","OpenedDocuments":"[\"Main.xaml\",\"Segment_Buys.xaml\",\"Tagging Screen.xaml\",\"Process.xaml\"]","ProjectBreakpoints":"{\"Value\":{\"Segment_Buys.xaml\":[{\"ConditionalExpression\":null,\"ActionExpression\":null,\"ExpectedHitCounter\":null,\"ShouldContinueAfterAction\":false,\"IsEnabled\":true,\"ActivityIdRef\":\"InvokeWorkflowFile_1\",\"ActivityId\":\"1.84\",\"ActivityName\":\"Invoke Identify Segment Row workflow\"}],\"Main.xaml\":[{\"ConditionalExpression\":null,\"ActionExpression\":null,\"ExpectedHitCounter\":null,\"ShouldContinueAfterAction\":false,\"IsEnabled\":true,\"ActivityIdRef\":\"InvokeWorkflowFile_20\",\"ActivityId\":\"1.182\",\"ActivityName\":\"Invoke GetTransactionData workflow\"}]}}"}